ittopjournal/__init__.py
ittopjournal/config.py
ittopjournal/core.py
ittopjournal-0.1.0.dist-info/licenses/LICENSE
ittopjournal-0.1.0.dist-info/METADATA
ittopjournal-0.1.0.dist-info/WHEEL
ittopjournal-0.1.0.dist-info/top_level.txt
ittopjournal-0.1.0.dist-info/RECORD
