Metadata-Version: 2.4
Name: ittopjournal
Version: 0.1.0
Summary: Python-библиотека для работы с API колледжа ITTOP (journal.top-academy.ru)
Author-email: Neitan Rudinsky <rudinskyneitan@gmail.com>
License: MIT
Project-URL: Homepage, https://github.com/neitan001/ittopjournal-Python-SDK
Requires-Python: >=3.7
License-File: LICENSE
Requires-Dist: requests>=2.25.0
Requires-Dist: pydantic>=1.10.0
Dynamic: license-file
